Metadata-Version: 2.1
Name: odoo14-addon-base-tier-validation-server-action
Version: 14.0.2.0.0
Summary: Add option to call server action when a tier is validated
Home-page: https://github.com/OCA/server-ux
Author: Ecosoft, Odoo Community Association (OCA)
Author-email: support@odoo-community.org
License: AGPL-3
Platform: UNKNOWN
Classifier: Programming Language :: Python
Classifier: Framework :: Odoo
Classifier: Framework :: Odoo :: 14.0
Classifier: License :: OSI Approved :: GNU Affero General Public License v3
Classifier: Development Status :: 4 - Beta
Requires-Python: >=3.6
Requires-Dist: odoo14-addon-base-tier-validation
Requires-Dist: odoo <14.1dev,>=14.0a
